mifarepy/__init__.py
mifarepy/protocol.py
mifarepy/reader.py
mifarepy-2.0.dist-info/LICENSE
mifarepy-2.0.dist-info/METADATA
mifarepy-2.0.dist-info/WHEEL
mifarepy-2.0.dist-info/top_level.txt
mifarepy-2.0.dist-info/RECORD
