Metadata-Version: 2.1
Name: mifarepy
Version: 2.0
Summary: Python library for interfacing with MIFARE RFID card readers using mifarepy protocol
Author-email: Spark Drago <huzaifa.farooq05@gmail.com>
License: GNU LESSER GENERAL PUBLIC LICENSE
Classifier: License :: OSI Approved :: GNU Lesser General Public License v3 (LGPLv3)
Classifier: Programming Language :: Python :: 3
Classifier: Operating System :: OS Independent
Requires-Python: >=3.6
License-File: LICENSE
Requires-Dist: pyserial
